worldtimepy/CONSTANTS.py
worldtimepy/__init__.py
worldtimepy/timeinfo.py
worldtimepy/worldtime.py
worldtimepy-0.1.1.dist-info/LICENSE
worldtimepy-0.1.1.dist-info/METADATA
worldtimepy-0.1.1.dist-info/WHEEL
worldtimepy-0.1.1.dist-info/top_level.txt
worldtimepy-0.1.1.dist-info/RECORD
