Metadata-Version: 2.1
Name: worldtimepy
Version: 0.1.1
Summary: A wrapper for WorldtimeAPI with search functionality.
Home-page: https://github.com/walero-moon/Worldtime-py
License: GPL-3.0
Project-URL: My GitHub, https://github.com/walero-moon
Project-URL: Source, https://github.com/walero-moon/Worldtime-py
Keywords: worldtimeAPI,worldtime-py,timezones,timezone-api,wrapper
Platform: UNKNOWN
Classifier: Programming Language :: Python :: 3
Classifier: License :: OSI Approved :: GNU General Public License v3 (GPLv3)
Classifier: Operating System :: OS Independent
Requires-Python: >=3.6
License-File: LICENSE
Requires-Dist: countryinfo
Requires-Dist: requests
Requires-Dist: unidecode
